julian_calc/__init__.py
julian_calc/coolstuff.py
julian_calc/main.py
julian_calc/areas/IrrAreas.py
julian_calc/areas/__init__.py
julian_calc/areas/areas.py
julian_calc/areas/areas2D.py
julian_calc/areas/areas3D.py
julian_calc/areas/test_irr_polygon.py
julian_calc/arithmetic/__init__.py
julian_calc/arithmetic/arithmetic.py
julian_calc/graphics/graph.py
julian_calc/trigonometry/__init__.py
julian_calc/trigonometry/trig.py
julian_calc-0.0.1.dist-info/METADATA
julian_calc-0.0.1.dist-info/WHEEL
julian_calc-0.0.1.dist-info/entry_points.txt
julian_calc-0.0.1.dist-info/top_level.txt
julian_calc-0.0.1.dist-info/RECORD
